OracleDBLibrary/__init__.py
OracleDBLibrary/base/__init__.py
OracleDBLibrary/base/oracle_base.py
OracleDBLibrary/decorator/__init__.py
OracleDBLibrary/decorator/singleton.py
OracleDBLibrary/keywords/__init__.py
OracleDBLibrary/keywords/oracle_connection.py
OracleDBLibrary/keywords/oracle_cursor.py
OracleDBLibrary/keywords/oracle_session_pool.py
OracleDBLibrary/keywords/oracle_var.py
OracleDBLibrary/mapper/__init__.py
OracleDBLibrary/mapper/argument_mapper.py
robotframework_oracledb_library-0.1.4.dist-info/LICENSE
robotframework_oracledb_library-0.1.4.dist-info/METADATA
robotframework_oracledb_library-0.1.4.dist-info/WHEEL
robotframework_oracledb_library-0.1.4.dist-info/top_level.txt
robotframework_oracledb_library-0.1.4.dist-info/RECORD
