Metadata-Version: 2.1
Name: robotframework-oracledb-library
Version: 0.1.4
Summary: Oracle database library for Robot Framework
Home-page: https://github.com/adeliogullari/robotframework-oracledb-library
Author: Abdullah Deliogullari
Author-email: abdullahdeliogullari@yaani.com
License: Apache License 2.0
Keywords: robotframework testing testautomation oracle database
Platform: any
Classifier: Development Status :: 5 - Production/Stable
Classifier: License :: OSI Approved :: Apache Software License
Classifier: Operating System :: OS Independent
Classifier: Programming Language :: Python
Classifier: Programming Language :: Python :: 3
Classifier: Programming Language :: Python :: 3.6
Classifier: Programming Language :: Python :: 3.7
Classifier: Programming Language :: Python :: 3.8
Classifier: Programming Language :: Python :: 3.9
Classifier: Programming Language :: Python :: 3.10
Classifier: Programming Language :: Python :: 3.11
Classifier: Programming Language :: Python :: 3 :: Only
Classifier: Topic :: Software Development :: Testing
Classifier: Framework :: Robot Framework
Classifier: Framework :: Robot Framework :: Library
Requires-Python: >=3.6, <4
License-File: LICENSE
Requires-Dist: oracledb >=2.0.0
Requires-Dist: robotframework >=6.1.1
Requires-Dist: robotframework-pythonlibcore >=4.3.0
